busbar/core/__init__.py
busbar/core/api/__init__.py
busbar/core/api/client.py
busbar/core/api/decorators.py
busbar/core/audit/__init__.py
busbar/core/audit/base.py
busbar/core/busbar.d/.order.yml
busbar/core/busbar.d/capabilities/.order.yml
busbar/core/busbar.d/capabilities/auth.yml
busbar/core/busbar.yml
busbar/core/config/__init__.py
busbar/core/config/base.py
busbar/core/config/loader.py
busbar/core/config/merge.py
busbar/core/config/models.py
busbar/core/containers.py
busbar/core/exceptions.py
busbar/core/models/__init__.py
busbar/core/models/base.py
busbar/core/modules/__init__.py
busbar/core/modules/base.py
busbar/core/providers/__init__.py
busbar/core/providers/base.py
busbar/core/providers/capabilities.py
busbar/core/security/__init__.py
busbar/core/security/config.py
busbar/core/security/events.py
busbar/core/security/incident.py
busbar/core/security/integrity.py
busbar/core/security/models.py
busbar/core/security/security_service.py
busbar/core/security/services.py
busbar/core/signals/__init__.py
busbar/core/signals/base.py
busbar/core/types.py
busbar/core/version.py
busbar_core-0.0.1.dist-info/METADATA
busbar_core-0.0.1.dist-info/WHEEL
busbar_core-0.0.1.dist-info/RECORD
